cutepy/__init__.py
cutepy/cutepy.py
cutepy-0.0.4.dist-info/METADATA
cutepy-0.0.4.dist-info/WHEEL
cutepy-0.0.4.dist-info/top_level.txt
cutepy-0.0.4.dist-info/RECORD
