Metadata-Version: 2.1
Name: cutepy
Version: 0.0.4
Summary: A helpfull python package!
Home-page: UNKNOWN
Author: Birdlinux (G. P.)
Author-email: <prepakis.geo@gmail.com>
License: UNKNOWN
Keywords: python,python system Detection,python hex,python rgb,python hex,python loader,rich python,python rich,cutepy
Platform: UNKNOWN
